tfv/__init__.py
tfv/_grid_to_tfv.py
tfv/extractor.py
tfv/geometry.py
tfv/miscellaneous.py
tfv/mldatetime.py
tfv/particles.py
tfv/restart.py
tfv/timeseries.py
tfv/viewer.py
tfv/visual.py
tfv/xarray.py
tfv-1.0.14.dist-info/licenses/LICENSE
tfv-1.0.14.dist-info/METADATA
tfv-1.0.14.dist-info/WHEEL
tfv-1.0.14.dist-info/top_level.txt
tfv-1.0.14.dist-info/RECORD
