Metadata-Version: 2.4
Name: tfv
Version: 1.0.14
Summary: Post processing tools for TUFLOW FV results
Home-page: https://gitlab.com/tuflow-user-group/tuflow-fv/tfv
Author: TUFLOW Support
Author-email: support@tuflow.com
License: MIT License
Classifier: Programming Language :: Python :: 3
Classifier: License :: OSI Approved :: MIT License
Classifier: Operating System :: OS Independent
Requires-Python: >=3.9
License-File: LICENSE
Requires-Dist: numpy>=1.24.0
Requires-Dist: matplotlib>=3.7.0
Requires-Dist: netCDF4>=1.6.3
Requires-Dist: xarray>=2023.1.0
Requires-Dist: dask>=2023.1.0
Requires-Dist: scipy>=1.10.0
Requires-Dist: tqdm>=4.65.0
Requires-Dist: pyproj>=3.5.0
Requires-Dist: geopandas>=0.13.0
Requires-Dist: shapely>=2.0.0
Requires-Dist: rioxarray>=0.13.0
Requires-Dist: ipywidgets>=8.0.0
Requires-Dist: ipympl>=0.9.0
Provides-Extra: viewer
Requires-Dist: PyQt5>=5.15.0; extra == "viewer"
Dynamic: license-file
